bencode/__init__.py
bencode/_bencode.c
bencode/_bencode.py
bencode/_bencodec.cp310-win_amd64.pyd
bencode/_fake_cython.py
bencode/utils.py
bencode_cy-1.2.2.dist-info/METADATA
bencode_cy-1.2.2.dist-info/WHEEL
bencode_cy-1.2.2.dist-info/top_level.txt
bencode_cy-1.2.2.dist-info/RECORD
