Metadata-Version: 2.4
Name: bencode.cy
Version: 1.2.2
Summary: A fast bencode implementation in Cython that supports Python 3. It uses Cython's pure Python syntax.
License-Expression: MIT
Project-URL: Homepage, https://github.com/touxiaoling/bencode.cy
Project-URL: Repository, https://github.com/touxiaoling/bencode.cy
Project-URL: Issues, https://github.com/touxiaoling/bencode.cy/issues
Keywords: bencode,bencoder,bdecode,bittorrent,bencoding,cython
Classifier: Development Status :: 5 - Production/Stable
Classifier: Operating System :: OS Independent
Classifier: Programming Language :: Python
Classifier: Programming Language :: Python :: 3 :: Only
Requires-Python: >=3.9
